setuptools_antlr/__init__.py
setuptools_antlr/command.py
setuptools_antlr/util.py
setuptools_antlr/lib/LICENSE.txt
setuptools_antlr/lib/antlr-4.7.1-complete.jar
setuptools_antlr-0.4.0.dist-info/LICENSE
setuptools_antlr-0.4.0.dist-info/METADATA
setuptools_antlr-0.4.0.dist-info/WHEEL
setuptools_antlr-0.4.0.dist-info/entry_points.txt
setuptools_antlr-0.4.0.dist-info/top_level.txt
setuptools_antlr-0.4.0.dist-info/RECORD
